PyMHSS/__init__.py
PyMHSS/algorithms.py
pymhss-0.1.4.dist-info/METADATA
pymhss-0.1.4.dist-info/WHEEL
pymhss-0.1.4.dist-info/top_level.txt
pymhss-0.1.4.dist-info/RECORD
