Metadata-Version: 2.1
Name: pymhss
Version: 0.1.4
Author: Estevao Prado, Christopher Nemeth, Chris Sherlock
Maintainer-email: Estevao Prado <e.prado1@lancaster.ac.uk>
Project-URL: Paper, https://arxiv.org/pdf/2407.19602
Project-URL: GitHub, https://github.com/ebprado/MH-with-scalable-subsampling
Requires-Dist: tensorflow
Requires-Dist: tqdm
Requires-Dist: scipy
Requires-Dist: plotnine
Requires-Dist: pandas
